rs_pitch_seq.py
retrosheet_pitch_sequences-1.1.0.dist-info/DESCRIPTION.rst
retrosheet_pitch_sequences-1.1.0.dist-info/entry_points.txt
retrosheet_pitch_sequences-1.1.0.dist-info/METADATA
retrosheet_pitch_sequences-1.1.0.dist-info/metadata.json
retrosheet_pitch_sequences-1.1.0.dist-info/RECORD
retrosheet_pitch_sequences-1.1.0.dist-info/top_level.txt
retrosheet_pitch_sequences-1.1.0.dist-info/WHEEL
