Metadata-Version: 2.0
Name: retrosheet-pitch-sequences
Version: 1.1.0
Summary: Retrosheet at-bat ball/strike count state extraction
Home-page: https://github.com/mattdennewitz/retrosheet-pitch-sequences
Author: Matt Dennewitz
Author-email: mattdennewitz@gmail.com
License: UNKNOWN
Platform: UNKNOWN
Requires-Dist: click (==0.6)
Requires-Dist: prettytable (==0.7.2)
